quikdb/__init__.py
quikdb/__main__.py
quikdb/sdk.py
quikdb/config/__init__.py
quikdb/config/logger.py
quikdb/controllers/__init__.py
quikdb/controllers/authenticate_principals.py
quikdb/controllers/client.py
quikdb/controllers/create_principals.py
quikdb/controllers/deploy_local.py
quikdb/controllers/deploy_production.py
quikdb/controllers/get_principal.py
quikdb/controllers/install_dfx.py
quikdb/controllers/set_owner.py
quikdb/file_types/__init__.py
quikdb/file_types/app.py
quikdb/file_types/auth.py
quikdb/file_types/database.py
quikdb/file_types/database_did.py
quikdb/http/__init__.py
quikdb/http/activate_project.py
quikdb/http/authenticate_cli.py
quikdb/http/deactivate_project.py
quikdb/http/encrypt_data.py
quikdb/http/upload_code.py
quikdb/programs/__init__.py
quikdb/programs/prg_config.py
quikdb/programs/prg_install.py
quikdb/utils/__init__.py
quikdb/utils/constants.py
quikdb/utils/toolbox.py
quikdb_cli-0.0.5.dist-info/LICENSE
quikdb_cli-0.0.5.dist-info/METADATA
quikdb_cli-0.0.5.dist-info/WHEEL
quikdb_cli-0.0.5.dist-info/top_level.txt
quikdb_cli-0.0.5.dist-info/RECORD
