Metadata-Version: 2.2
Name: quikdb-cli
Version: 0.0.5
Summary: it provides a way to interact with the database in blockchain
Author-email: Kunle Adewole <adewoleadekunle23@yahoo.com>, Samson ajulor <samsonajulor@gmail.com>
Project-URL: Homepage, https://github.com/pypa/sampleproject
Project-URL: Issues, https://github.com/pypa/sampleproject/issues
Classifier: Programming Language :: Python :: 3
Classifier: License :: OSI Approved :: MIT License
Classifier: Operating System :: OS Independent
Requires-Python: >=3.8
License-File: LICENSE
Requires-Dist: email_validator==2.2.0
Requires-Dist: requests==2.32.3
